sblgntparser/parser.py
sblgntparser/model.py
sblgntparser/tools.py
sblgntparser/__init__.py
sblgntparser/codes.py
sblgntparser/particles.json
sblgntparser-0.4.3.dist-info/metadata.json
sblgntparser-0.4.3.dist-info/RECORD
sblgntparser-0.4.3.dist-info/DESCRIPTION.rst
sblgntparser-0.4.3.dist-info/WHEEL
sblgntparser-0.4.3.dist-info/top_level.txt
sblgntparser-0.4.3.dist-info/METADATA
