Metadata-Version: 2.0
Name: sblgntparser
Version: 0.4.3
Summary: This packages provides a python 3 parser and tools for the SBL Greek New Testament format.
Home-page: https://github.com/KLINGTdotNET/sblgntparser
Author: Andreas Linz
Author-email: klingt.net@gmail.com
License: MIT
Download-URL: https://github.com/KLINGTdotNET/sblgntparser/archive/0.1.tar.gz
Keywords: sblgnt parser
Platform: UNKNOWN
